{"nodes": [{"id": "e_web_craveva_staging_packages_macsidigital_laravel_zoom_src_exceptions_filetoolargeexception_php", "label": "FileTooLargeException.php", "file_type": "code", "source_file": "E:\\web\\craveva-staging\\packages\\macsidigital-laravel-zoom\\src\\Exceptions\\FileTooLargeException.php", "source_location": "L1"}, {"id": "exceptions_filetoolargeexception_filetoolargeexception", "label": "FileTooLargeException", "file_type": "code", "source_file": "E:\\web\\craveva-staging\\packages\\macsidigital-laravel-zoom\\src\\Exceptions\\FileTooLargeException.php", "source_location": "L7"}, {"id": "exceptions_filetoolargeexception_filetoolargeexception_construct", "label": ".__construct()", "file_type": "code", "source_file": "E:\\web\\craveva-staging\\packages\\macsidigital-laravel-zoom\\src\\Exceptions\\FileTooLargeException.php", "source_location": "L9"}], "edges": [{"source": "e_web_craveva_staging_packages_macsidigital_laravel_zoom_src_exceptions_filetoolargeexception_php", "target": "exception", "relation": "imports", "confidence": "EXTRACTED", "source_file": "E:\\web\\craveva-staging\\packages\\macsidigital-laravel-zoom\\src\\Exceptions\\FileTooLargeException.php", "source_location": "L5", "weight": 1.0}, {"source": "e_web_craveva_staging_packages_macsidigital_laravel_zoom_src_exceptions_filetoolargeexception_php", "target": "exceptions_filetoolargeexception_filetoolargeexception", "relation": "contains", "confidence": "EXTRACTED", "source_file": "E:\\web\\craveva-staging\\packages\\macsidigital-laravel-zoom\\src\\Exceptions\\FileTooLargeException.php", "source_location": "L7", "weight": 1.0}, {"source": "exceptions_filetoolargeexception_filetoolargeexception", "target": "exceptions_filetoolargeexception_filetoolargeexception_construct", "relation": "method", "confidence": "EXTRACTED", "source_file": "E:\\web\\craveva-staging\\packages\\macsidigital-laravel-zoom\\src\\Exceptions\\FileTooLargeException.php", "source_location": "L9", "weight": 1.0}], "raw_calls": [{"caller_nid": "exceptions_filetoolargeexception_filetoolargeexception_construct", "callee": "parent", "source_file": "E:\\web\\craveva-staging\\packages\\macsidigital-laravel-zoom\\src\\Exceptions\\FileTooLargeException.php", "source_location": "L11"}]}