{"nodes": [{"id": "e_web_craveva_staging_modules_projectroadmap_resources_views_table_milestones_list_blade_php", "label": "milestones-list.blade.php", "file_type": "code", "source_file": "E:\\web\\craveva-staging\\Modules\\ProjectRoadmap\\Resources\\views\\table\\milestones-list.blade.php", "source_location": null}, {"id": "sections_datatable_css", "label": "sections.datatable_css", "file_type": "code", "source_file": "E:\\web\\craveva-staging\\Modules\\ProjectRoadmap\\Resources\\views\\table\\milestones-list.blade.php", "source_location": null}], "edges": [{"source": "e_web_craveva_staging_modules_projectroadmap_resources_views_table_milestones_list_blade_php", "target": "sections_datatable_css", "relation": "includes", "confidence": "EXTRACTED", "confidence_score": 1.0, "source_file": "E:\\web\\craveva-staging\\Modules\\ProjectRoadmap\\Resources\\views\\table\\milestones-list.blade.php", "source_location": null, "weight": 1.0}]}