{"nodes": [{"id": "e_web_craveva_staging_packages_mitchbred_entrust_l11_src_entrust_entrustserviceprovider_php", "label": "EntrustServiceProvider.php", "file_type": "code", "source_file": "E:\\web\\craveva-staging\\packages\\mitchbred-entrust-l11\\src\\Entrust\\EntrustServiceProvider.php", "source_location": "L1"}, {"id": "entrust_entrustserviceprovider_entrustserviceprovider", "label": "EntrustServiceProvider", "file_type": "code", "source_file": "E:\\web\\craveva-staging\\packages\\mitchbred-entrust-l11\\src\\Entrust\\EntrustServiceProvider.php", "source_location": "L18"}, {"id": "entrust_entrustserviceprovider_entrustserviceprovider_boot", "label": ".boot()", "file_type": "code", "source_file": "E:\\web\\craveva-staging\\packages\\mitchbred-entrust-l11\\src\\Entrust\\EntrustServiceProvider.php", "source_location": "L30"}, {"id": "entrust_entrustserviceprovider_entrustserviceprovider_register", "label": ".register()", "file_type": "code", "source_file": "E:\\web\\craveva-staging\\packages\\mitchbred-entrust-l11\\src\\Entrust\\EntrustServiceProvider.php", "source_location": "L47"}, {"id": "entrust_entrustserviceprovider_entrustserviceprovider_bladedirectives", "label": ".bladeDirectives()", "file_type": "code", "source_file": "E:\\web\\craveva-staging\\packages\\mitchbred-entrust-l11\\src\\Entrust\\EntrustServiceProvider.php", "source_location": "L60"}, {"id": "entrust_entrustserviceprovider_entrustserviceprovider_registerentrust", "label": ".registerEntrust()", "file_type": "code", "source_file": "E:\\web\\craveva-staging\\packages\\mitchbred-entrust-l11\\src\\Entrust\\EntrustServiceProvider.php", "source_location": "L85"}, {"id": "entrust_entrustserviceprovider_entrustserviceprovider_registercommands", "label": ".registerCommands()", "file_type": "code", "source_file": "E:\\web\\craveva-staging\\packages\\mitchbred-entrust-l11\\src\\Entrust\\EntrustServiceProvider.php", "source_location": "L95"}, {"id": "entrust_entrustserviceprovider_entrustserviceprovider_mergeconfig", "label": ".mergeConfig()", "file_type": "code", "source_file": "E:\\web\\craveva-staging\\packages\\mitchbred-entrust-l11\\src\\Entrust\\EntrustServiceProvider.php", "source_location": "L103"}, {"id": "entrust_entrustserviceprovider_entrustserviceprovider_provides", "label": ".provides()", "file_type": "code", "source_file": "E:\\web\\craveva-staging\\packages\\mitchbred-entrust-l11\\src\\Entrust\\EntrustServiceProvider.php", "source_location": "L115"}], "edges": [{"source": "e_web_craveva_staging_packages_mitchbred_entrust_l11_src_entrust_entrustserviceprovider_php", "target": "blade", "relation": "imports", "confidence": "EXTRACTED", "source_file": "E:\\web\\craveva-staging\\packages\\mitchbred-entrust-l11\\src\\Entrust\\EntrustServiceProvider.php", "source_location": "L15", "weight": 1.0}, {"source": "e_web_craveva_staging_packages_mitchbred_entrust_l11_src_entrust_entrustserviceprovider_php", "target": "serviceprovider", "relation": "imports", "confidence": "EXTRACTED", "source_file": "E:\\web\\craveva-staging\\packages\\mitchbred-entrust-l11\\src\\Entrust\\EntrustServiceProvider.php", "source_location": "L16", "weight": 1.0}, {"source": "e_web_craveva_staging_packages_mitchbred_entrust_l11_src_entrust_entrustserviceprovider_php", "target": "entrust_entrustserviceprovider_entrustserviceprovider", "relation": "contains", "confidence": "EXTRACTED", "source_file": "E:\\web\\craveva-staging\\packages\\mitchbred-entrust-l11\\src\\Entrust\\EntrustServiceProvider.php", "source_location": "L18", "weight": 1.0}, {"source": "entrust_entrustserviceprovider_entrustserviceprovider", "target": "entrust_entrustserviceprovider_entrustserviceprovider_boot", "relation": "method", "confidence": "EXTRACTED", "source_file": "E:\\web\\craveva-staging\\packages\\mitchbred-entrust-l11\\src\\Entrust\\EntrustServiceProvider.php", "source_location": "L30", "weight": 1.0}, {"source": "entrust_entrustserviceprovider_entrustserviceprovider", "target": "entrust_entrustserviceprovider_entrustserviceprovider_register", "relation": "method", "confidence": "EXTRACTED", "source_file": "E:\\web\\craveva-staging\\packages\\mitchbred-entrust-l11\\src\\Entrust\\EntrustServiceProvider.php", "source_location": "L47", "weight": 1.0}, {"source": "entrust_entrustserviceprovider_entrustserviceprovider", "target": "entrust_entrustserviceprovider_entrustserviceprovider_bladedirectives", "relation": "method", "confidence": "EXTRACTED", "source_file": "E:\\web\\craveva-staging\\packages\\mitchbred-entrust-l11\\src\\Entrust\\EntrustServiceProvider.php", "source_location": "L60", "weight": 1.0}, {"source": "entrust_entrustserviceprovider_entrustserviceprovider", "target": "entrust_entrustserviceprovider_entrustserviceprovider_registerentrust", "relation": "method", "confidence": "EXTRACTED", "source_file": "E:\\web\\craveva-staging\\packages\\mitchbred-entrust-l11\\src\\Entrust\\EntrustServiceProvider.php", "source_location": "L85", "weight": 1.0}, {"source": "entrust_entrustserviceprovider_entrustserviceprovider", "target": "entrust_entrustserviceprovider_entrustserviceprovider_registercommands", "relation": "method", "confidence": "EXTRACTED", "source_file": "E:\\web\\craveva-staging\\packages\\mitchbred-entrust-l11\\src\\Entrust\\EntrustServiceProvider.php", "source_location": "L95", "weight": 1.0}, {"source": "entrust_entrustserviceprovider_entrustserviceprovider", "target": "entrust_entrustserviceprovider_entrustserviceprovider_mergeconfig", "relation": "method", "confidence": "EXTRACTED", "source_file": "E:\\web\\craveva-staging\\packages\\mitchbred-entrust-l11\\src\\Entrust\\EntrustServiceProvider.php", "source_location": "L103", "weight": 1.0}, {"source": "entrust_entrustserviceprovider_entrustserviceprovider", "target": "entrust_entrustserviceprovider_entrustserviceprovider_provides", "relation": "method", "confidence": "EXTRACTED", "source_file": "E:\\web\\craveva-staging\\packages\\mitchbred-entrust-l11\\src\\Entrust\\EntrustServiceProvider.php", "source_location": "L115", "weight": 1.0}, {"source": "entrust_entrustserviceprovider_entrustserviceprovider_boot", "target": "entrust_entrustserviceprovider_entrustserviceprovider_bladedirectives", "relation": "calls", "confidence": "EXTRACTED", "source_file": "E:\\web\\craveva-staging\\packages\\mitchbred-entrust-l11\\src\\Entrust\\EntrustServiceProvider.php", "source_location": "L41", "weight": 1.0}, {"source": "entrust_entrustserviceprovider_entrustserviceprovider_register", "target": "entrust_entrustserviceprovider_entrustserviceprovider_registerentrust", "relation": "calls", "confidence": "EXTRACTED", "source_file": "E:\\web\\craveva-staging\\packages\\mitchbred-entrust-l11\\src\\Entrust\\EntrustServiceProvider.php", "source_location": "L50", "weight": 1.0}, {"source": "entrust_entrustserviceprovider_entrustserviceprovider_register", "target": "entrust_entrustserviceprovider_entrustserviceprovider_registercommands", "relation": "calls", "confidence": "EXTRACTED", "source_file": "E:\\web\\craveva-staging\\packages\\mitchbred-entrust-l11\\src\\Entrust\\EntrustServiceProvider.php", "source_location": "L52", "weight": 1.0}, {"source": "entrust_entrustserviceprovider_entrustserviceprovider_register", "target": "entrust_entrustserviceprovider_entrustserviceprovider_mergeconfig", "relation": "calls", "confidence": "EXTRACTED", "source_file": "E:\\web\\craveva-staging\\packages\\mitchbred-entrust-l11\\src\\Entrust\\EntrustServiceProvider.php", "source_location": "L54", "weight": 1.0}], "raw_calls": [{"caller_nid": "entrust_entrustserviceprovider_entrustserviceprovider_boot", "callee": "publishes", "source_file": "E:\\web\\craveva-staging\\packages\\mitchbred-entrust-l11\\src\\Entrust\\EntrustServiceProvider.php", "source_location": "L33"}, {"caller_nid": "entrust_entrustserviceprovider_entrustserviceprovider_boot", "callee": "basePath", "source_file": "E:\\web\\craveva-staging\\packages\\mitchbred-entrust-l11\\src\\Entrust\\EntrustServiceProvider.php", "source_location": "L34"}, {"caller_nid": "entrust_entrustserviceprovider_entrustserviceprovider_boot", "callee": "app", "source_file": "E:\\web\\craveva-staging\\packages\\mitchbred-entrust-l11\\src\\Entrust\\EntrustServiceProvider.php", "source_location": "L34"}, {"caller_nid": "entrust_entrustserviceprovider_entrustserviceprovider_boot", "callee": "commands", "source_file": "E:\\web\\craveva-staging\\packages\\mitchbred-entrust-l11\\src\\Entrust\\EntrustServiceProvider.php", "source_location": "L38"}, {"caller_nid": "entrust_entrustserviceprovider_entrustserviceprovider_bladedirectives", "callee": "class_exists", "source_file": "E:\\web\\craveva-staging\\packages\\mitchbred-entrust-l11\\src\\Entrust\\EntrustServiceProvider.php", "source_location": "L62"}, {"caller_nid": "entrust_entrustserviceprovider_entrustserviceprovider_bladedirectives", "callee": "Blade", "source_file": "E:\\web\\craveva-staging\\packages\\mitchbred-entrust-l11\\src\\Entrust\\EntrustServiceProvider.php", "source_location": "L67"}, {"caller_nid": "entrust_entrustserviceprovider_entrustserviceprovider_bladedirectives", "callee": "sprintf", "source_file": "E:\\web\\craveva-staging\\packages\\mitchbred-entrust-l11\\src\\Entrust\\EntrustServiceProvider.php", "source_location": "L67"}, {"caller_nid": "entrust_entrustserviceprovider_entrustserviceprovider_bladedirectives", "callee": "Blade", "source_file": "E:\\web\\craveva-staging\\packages\\mitchbred-entrust-l11\\src\\Entrust\\EntrustServiceProvider.php", "source_location": "L69"}, {"caller_nid": "entrust_entrustserviceprovider_entrustserviceprovider_bladedirectives", "callee": "Blade", "source_file": "E:\\web\\craveva-staging\\packages\\mitchbred-entrust-l11\\src\\Entrust\\EntrustServiceProvider.php", "source_location": "L72"}, {"caller_nid": "entrust_entrustserviceprovider_entrustserviceprovider_bladedirectives", "callee": "sprintf", "source_file": "E:\\web\\craveva-staging\\packages\\mitchbred-entrust-l11\\src\\Entrust\\EntrustServiceProvider.php", "source_location": "L72"}, {"caller_nid": "entrust_entrustserviceprovider_entrustserviceprovider_bladedirectives", "callee": "Blade", "source_file": "E:\\web\\craveva-staging\\packages\\mitchbred-entrust-l11\\src\\Entrust\\EntrustServiceProvider.php", "source_location": "L74"}, {"caller_nid": "entrust_entrustserviceprovider_entrustserviceprovider_bladedirectives", "callee": "Blade", "source_file": "E:\\web\\craveva-staging\\packages\\mitchbred-entrust-l11\\src\\Entrust\\EntrustServiceProvider.php", "source_location": "L77"}, {"caller_nid": "entrust_entrustserviceprovider_entrustserviceprovider_bladedirectives", "callee": "sprintf", "source_file": "E:\\web\\craveva-staging\\packages\\mitchbred-entrust-l11\\src\\Entrust\\EntrustServiceProvider.php", "source_location": "L77"}, {"caller_nid": "entrust_entrustserviceprovider_entrustserviceprovider_bladedirectives", "callee": "Blade", "source_file": "E:\\web\\craveva-staging\\packages\\mitchbred-entrust-l11\\src\\Entrust\\EntrustServiceProvider.php", "source_location": "L79"}, {"caller_nid": "entrust_entrustserviceprovider_entrustserviceprovider_registerentrust", "callee": "bind", "source_file": "E:\\web\\craveva-staging\\packages\\mitchbred-entrust-l11\\src\\Entrust\\EntrustServiceProvider.php", "source_location": "L87"}, {"caller_nid": "entrust_entrustserviceprovider_entrustserviceprovider_registerentrust", "callee": "alias", "source_file": "E:\\web\\craveva-staging\\packages\\mitchbred-entrust-l11\\src\\Entrust\\EntrustServiceProvider.php", "source_location": "L89"}, {"caller_nid": "entrust_entrustserviceprovider_entrustserviceprovider_registercommands", "callee": "singleton", "source_file": "E:\\web\\craveva-staging\\packages\\mitchbred-entrust-l11\\src\\Entrust\\EntrustServiceProvider.php", "source_location": "L97"}, {"caller_nid": "entrust_entrustserviceprovider_entrustserviceprovider_mergeconfig", "callee": "mergeConfigFrom", "source_file": "E:\\web\\craveva-staging\\packages\\mitchbred-entrust-l11\\src\\Entrust\\EntrustServiceProvider.php", "source_location": "L105"}]}