{"nodes": [{"id": "e_web_craveva_staging_modules_affiliate_enums_payoutmethod_php", "label": "PayoutMethod.php", "file_type": "code", "source_file": "E:\\web\\craveva-staging\\Modules\\Affiliate\\Enums\\PayoutMethod.php", "source_location": "L1"}, {"id": "enums_payoutmethod_label", "label": "label()", "file_type": "code", "source_file": "E:\\web\\craveva-staging\\Modules\\Affiliate\\Enums\\PayoutMethod.php", "source_location": "L16"}], "edges": [{"source": "e_web_craveva_staging_modules_affiliate_enums_payoutmethod_php", "target": "enums_payoutmethod_label", "relation": "contains", "confidence": "EXTRACTED", "source_file": "E:\\web\\craveva-staging\\Modules\\Affiliate\\Enums\\PayoutMethod.php", "source_location": "L16", "weight": 1.0}], "raw_calls": [{"caller_nid": "enums_payoutmethod_label", "callee": "__", "source_file": "E:\\web\\craveva-staging\\Modules\\Affiliate\\Enums\\PayoutMethod.php", "source_location": "L19"}, {"caller_nid": "enums_payoutmethod_label", "callee": "__", "source_file": "E:\\web\\craveva-staging\\Modules\\Affiliate\\Enums\\PayoutMethod.php", "source_location": "L20"}, {"caller_nid": "enums_payoutmethod_label", "callee": "__", "source_file": "E:\\web\\craveva-staging\\Modules\\Affiliate\\Enums\\PayoutMethod.php", "source_location": "L21"}]}