{"nodes": [{"id": "e_web_craveva_staging_modules_payroll_observers_salaryslipobserver_php", "label": "SalarySlipObserver.php", "file_type": "code", "source_file": "E:\\web\\craveva-staging\\Modules\\Payroll\\Observers\\SalarySlipObserver.php", "source_location": "L1"}, {"id": "observers_salaryslipobserver_salaryslipobserver", "label": "SalarySlipObserver", "file_type": "code", "source_file": "E:\\web\\craveva-staging\\Modules\\Payroll\\Observers\\SalarySlipObserver.php", "source_location": "L7"}, {"id": "observers_salaryslipobserver_salaryslipobserver_saving", "label": ".saving()", "file_type": "code", "source_file": "E:\\web\\craveva-staging\\Modules\\Payroll\\Observers\\SalarySlipObserver.php", "source_location": "L9"}, {"id": "observers_salaryslipobserver_salaryslipobserver_creating", "label": ".creating()", "file_type": "code", "source_file": "E:\\web\\craveva-staging\\Modules\\Payroll\\Observers\\SalarySlipObserver.php", "source_location": "L16"}], "edges": [{"source": "e_web_craveva_staging_modules_payroll_observers_salaryslipobserver_php", "target": "salaryslip", "relation": "imports", "confidence": "EXTRACTED", "source_file": "E:\\web\\craveva-staging\\Modules\\Payroll\\Observers\\SalarySlipObserver.php", "source_location": "L5", "weight": 1.0}, {"source": "e_web_craveva_staging_modules_payroll_observers_salaryslipobserver_php", "target": "observers_salaryslipobserver_salaryslipobserver", "relation": "contains", "confidence": "EXTRACTED", "source_file": "E:\\web\\craveva-staging\\Modules\\Payroll\\Observers\\SalarySlipObserver.php", "source_location": "L7", "weight": 1.0}, {"source": "observers_salaryslipobserver_salaryslipobserver", "target": "observers_salaryslipobserver_salaryslipobserver_saving", "relation": "method", "confidence": "EXTRACTED", "source_file": "E:\\web\\craveva-staging\\Modules\\Payroll\\Observers\\SalarySlipObserver.php", "source_location": "L9", "weight": 1.0}, {"source": "observers_salaryslipobserver_salaryslipobserver", "target": "observers_salaryslipobserver_salaryslipobserver_creating", "relation": "method", "confidence": "EXTRACTED", "source_file": "E:\\web\\craveva-staging\\Modules\\Payroll\\Observers\\SalarySlipObserver.php", "source_location": "L16", "weight": 1.0}], "raw_calls": [{"caller_nid": "observers_salaryslipobserver_salaryslipobserver_saving", "callee": "user", "source_file": "E:\\web\\craveva-staging\\Modules\\Payroll\\Observers\\SalarySlipObserver.php", "source_location": "L11"}, {"caller_nid": "observers_salaryslipobserver_salaryslipobserver_saving", "callee": "user", "source_file": "E:\\web\\craveva-staging\\Modules\\Payroll\\Observers\\SalarySlipObserver.php", "source_location": "L12"}, {"caller_nid": "observers_salaryslipobserver_salaryslipobserver_creating", "callee": "company", "source_file": "E:\\web\\craveva-staging\\Modules\\Payroll\\Observers\\SalarySlipObserver.php", "source_location": "L18"}, {"caller_nid": "observers_salaryslipobserver_salaryslipobserver_creating", "callee": "company", "source_file": "E:\\web\\craveva-staging\\Modules\\Payroll\\Observers\\SalarySlipObserver.php", "source_location": "L19"}]}