{"nodes": [{"id": "e_web_craveva_staging_app_http_requests_timelogs_storetimelog_php", "label": "StoreTimeLog.php", "file_type": "code", "source_file": "E:\\web\\craveva-staging\\app\\Http\\Requests\\TimeLogs\\StoreTimeLog.php", "source_location": "L1"}, {"id": "timelogs_storetimelog_storetimelog", "label": "StoreTimeLog", "file_type": "code", "source_file": "E:\\web\\craveva-staging\\app\\Http\\Requests\\TimeLogs\\StoreTimeLog.php", "source_location": "L8"}, {"id": "timelogs_storetimelog_storetimelog_authorize", "label": ".authorize()", "file_type": "code", "source_file": "E:\\web\\craveva-staging\\app\\Http\\Requests\\TimeLogs\\StoreTimeLog.php", "source_location": "L17"}, {"id": "timelogs_storetimelog_storetimelog_rules", "label": ".rules()", "file_type": "code", "source_file": "E:\\web\\craveva-staging\\app\\Http\\Requests\\TimeLogs\\StoreTimeLog.php", "source_location": "L27"}, {"id": "timelogs_storetimelog_storetimelog_attributes", "label": ".attributes()", "file_type": "code", "source_file": "E:\\web\\craveva-staging\\app\\Http\\Requests\\TimeLogs\\StoreTimeLog.php", "source_location": "L42"}, {"id": "timelogs_storetimelog_storetimelog_messages", "label": ".messages()", "file_type": "code", "source_file": "E:\\web\\craveva-staging\\app\\Http\\Requests\\TimeLogs\\StoreTimeLog.php", "source_location": "L51"}], "edges": [{"source": "e_web_craveva_staging_app_http_requests_timelogs_storetimelog_php", "target": "corerequest", "relation": "imports", "confidence": "EXTRACTED", "source_file": "E:\\web\\craveva-staging\\app\\Http\\Requests\\TimeLogs\\StoreTimeLog.php", "source_location": "L5", "weight": 1.0}, {"source": "e_web_craveva_staging_app_http_requests_timelogs_storetimelog_php", "target": "customfieldsrequesttrait", "relation": "imports", "confidence": "EXTRACTED", "source_file": "E:\\web\\craveva-staging\\app\\Http\\Requests\\TimeLogs\\StoreTimeLog.php", "source_location": "L6", "weight": 1.0}, {"source": "e_web_craveva_staging_app_http_requests_timelogs_storetimelog_php", "target": "timelogs_storetimelog_storetimelog", "relation": "contains", "confidence": "EXTRACTED", "source_file": "E:\\web\\craveva-staging\\app\\Http\\Requests\\TimeLogs\\StoreTimeLog.php", "source_location": "L8", "weight": 1.0}, {"source": "timelogs_storetimelog_storetimelog", "target": "timelogs_storetimelog_storetimelog_authorize", "relation": "method", "confidence": "EXTRACTED", "source_file": "E:\\web\\craveva-staging\\app\\Http\\Requests\\TimeLogs\\StoreTimeLog.php", "source_location": "L17", "weight": 1.0}, {"source": "timelogs_storetimelog_storetimelog", "target": "timelogs_storetimelog_storetimelog_rules", "relation": "method", "confidence": "EXTRACTED", "source_file": "E:\\web\\craveva-staging\\app\\Http\\Requests\\TimeLogs\\StoreTimeLog.php", "source_location": "L27", "weight": 1.0}, {"source": "timelogs_storetimelog_storetimelog", "target": "timelogs_storetimelog_storetimelog_attributes", "relation": "method", "confidence": "EXTRACTED", "source_file": "E:\\web\\craveva-staging\\app\\Http\\Requests\\TimeLogs\\StoreTimeLog.php", "source_location": "L42", "weight": 1.0}, {"source": "timelogs_storetimelog_storetimelog", "target": "timelogs_storetimelog_storetimelog_messages", "relation": "method", "confidence": "EXTRACTED", "source_file": "E:\\web\\craveva-staging\\app\\Http\\Requests\\TimeLogs\\StoreTimeLog.php", "source_location": "L51", "weight": 1.0}], "raw_calls": [{"caller_nid": "timelogs_storetimelog_storetimelog_rules", "callee": "customFieldRules", "source_file": "E:\\web\\craveva-staging\\app\\Http\\Requests\\TimeLogs\\StoreTimeLog.php", "source_location": "L37"}, {"caller_nid": "timelogs_storetimelog_storetimelog_attributes", "callee": "customFieldsAttributes", "source_file": "E:\\web\\craveva-staging\\app\\Http\\Requests\\TimeLogs\\StoreTimeLog.php", "source_location": "L46"}, {"caller_nid": "timelogs_storetimelog_storetimelog_messages", "callee": "__", "source_file": "E:\\web\\craveva-staging\\app\\Http\\Requests\\TimeLogs\\StoreTimeLog.php", "source_location": "L54"}, {"caller_nid": "timelogs_storetimelog_storetimelog_messages", "callee": "__", "source_file": "E:\\web\\craveva-staging\\app\\Http\\Requests\\TimeLogs\\StoreTimeLog.php", "source_location": "L55"}, {"caller_nid": "timelogs_storetimelog_storetimelog_messages", "callee": "__", "source_file": "E:\\web\\craveva-staging\\app\\Http\\Requests\\TimeLogs\\StoreTimeLog.php", "source_location": "L56"}]}